wqu/__init__.py
wqu/dp/__init__.py
wqu/dp/binomial.py
wqu/dp/black_scholes.py
wqu/dp/gbm.py
wqu/dp/montecarlo.py
wqu/dp/returns.py
wqu/dp/utils.py
wqu/dp/vasicek.py
wqu/pricing/__init__.py
wqu/pricing/binomial.py
wqu/pricing/greeks.py
wqu/pricing/hedging.py
wqu/pricing/options.py
wqu/pricing/trinomial.py
wqu/pricing/utils.py
wqu/sm/__init__.py
wqu/sm/bates.py
wqu/sm/black_scholes.py
wqu/sm/credit_rating.py
wqu/sm/heston.py
wqu/sm/markov.py
wqu/sm/merton.py
wqu/utils/__init__.py
wqu-0.2.11.dist-info/entry_points.txt
wqu-0.2.11.dist-info/licenses/LICENSE
wqu-0.2.11.dist-info/WHEEL
wqu-0.2.11.dist-info/METADATA
wqu-0.2.11.dist-info/RECORD
