Metadata-Version: 2.4
Name: wqu
Version: 0.2.11
Summary: Custom functions and classes build for the WQU courses
Author-email: Azat <8280770+azataiot@users.noreply.github.com>
Requires-Python: >=3.11
License-File: LICENSE
Requires-Dist: graphviz>=0.20.3
Requires-Dist: matplotlib>=3.10.0
Requires-Dist: pandas>=2.2.3
Requires-Dist: scipy>=1.15.2
Requires-Dist: seaborn>=0.13.2
Requires-Dist: yfinance>=0.2.55
Project-URL: documentation, https://azgh.cc/wqu/
Project-URL: repository, https://github.com/azataiot/wqu
